amis/AmisComponent.py
amis/__init__.py
amis/amis.py
amis/components/Action.py
amis/components/AjaxAction.py
amis/components/Alert.py
amis/components/Amis.py
amis/components/AnchorNav.py
amis/components/AnchorNavSection.py
amis/components/Api.py
amis/components/ApiObject.py
amis/components/App.py
amis/components/ArrayControl.py
amis/components/Audio.py
amis/components/AutoFillHeightObject.py
amis/components/AutoGenerateFilterObject.py
amis/components/Avatar.py
amis/components/Badge.py
amis/components/BadgeObject.py
amis/components/Barcode.py
amis/components/BaseApiObject.py
amis/components/Breadcrumb.py
amis/components/Button.py
amis/components/ButtonGroup.py
amis/components/ButtonGroupControl.py
amis/components/ButtonGroupSelect.py
amis/components/ButtonToolbar.py
amis/components/CRUD.py
amis/components/CRUD2.py
amis/components/CRUD2Cards.py
amis/components/CRUD2List.py
amis/components/CRUD2Table.py
amis/components/CRUDCards.py
amis/components/CRUDList.py
amis/components/CRUDTable.py
amis/components/Calendar.py
amis/components/Card.py
amis/components/Card2.py
amis/components/Cards.py
amis/components/Carousel.py
amis/components/ChainSelect.py
amis/components/ChainedSelectControl.py
amis/components/Chart.py
amis/components/ChartRadios.py
amis/components/Checkbox.py
amis/components/CheckboxControl.py
amis/components/Checkboxes.py
amis/components/CheckboxesControl.py
amis/components/ClassName.py
amis/components/Code.py
amis/components/Collapse.py
amis/components/CollapseGroup.py
amis/components/Collection.py
amis/components/Color.py
amis/components/Column.py
amis/components/Combo.py
amis/components/ComboControl.py
amis/components/ComboSubControl.py
amis/components/ConditionBuilder.py
amis/components/ConditionBuilderControl.py
amis/components/Container.py
amis/components/Control.py
amis/components/CopyAction.py
amis/components/Copyable.py
amis/components/CopyableObject.py
amis/components/Custom.py
amis/components/Date.py
amis/components/DateControl.py
python_amis-0.0.3.dist-info/METADATA
python_amis-0.0.3.dist-info/WHEEL
python_amis-0.0.3.dist-info/top_level.txt
python_amis-0.0.3.dist-info/RECORD
