Metadata-Version: 2.1
Name: python-amis
Version: 0.0.3
Summary: This is the Python version of the AMIS component encapsulated by Baidu. 
Home-page: https://github.com/duolabmeng6/py-amis
Author: duolabmeng6
Author-email: 1715109585@qq.com
Keywords: python-amis
Classifier: Programming Language :: Python :: 3
Classifier: License :: OSI Approved :: MIT License
Classifier: Operating System :: OS Independent
Requires-Python: >=3.6
